securities_exchange/__init__.py
securities_exchange/bookside.py
securities_exchange/enums.py
securities_exchange/order.py
securities_exchange/orderbook.py
securities_exchange/securities_exchange.py
securities_exchange-0.0.11.dist-info/LICENSE
securities_exchange-0.0.11.dist-info/METADATA
securities_exchange-0.0.11.dist-info/WHEEL
securities_exchange-0.0.11.dist-info/entry_points.txt
securities_exchange-0.0.11.dist-info/top_level.txt
securities_exchange-0.0.11.dist-info/RECORD
