Metadata-Version: 2.1
Name: securities-exchange
Version: 0.0.11
Summary: A toy example of a Security Exchange in python
Author-email: Giulio Guerri <giulio.guerri93@gmail.com>
License: MIT License
Project-URL: Homepage, https://github.com/ggnne/securities-exchange
Keywords: securities-exchange
Classifier: Intended Audience :: Developers
Classifier: License :: OSI Approved :: MIT License
Classifier: Natural Language :: English
Classifier: Programming Language :: Python :: 3.8
Classifier: Programming Language :: Python :: 3.9
Classifier: Programming Language :: Python :: 3.10
Classifier: Programming Language :: Python :: 3.11
Classifier: Programming Language :: Python :: 3.12
Requires-Python: >=3.8
License-File: LICENSE
Requires-Dist: numpy
Requires-Dist: pydantic
Provides-Extra: all
Requires-Dist: securities-exchange[extra] ; extra == 'all'
Provides-Extra: extra
Requires-Dist: pandas ; extra == 'extra'
